Workbook

Sheet INSTRUCTIONS
A2: Background: | B2: In preparation for the migration of IIS data to the new Regulatory Oversight Management System, it is important to identify groupings of companies based on the parent regulated entity.
A3: Purpose: | B3: Identify all companies that should be grouped together under a single/common parent company/regulated entity.
A4: Instructions: | B4: 1. Sort the COMPANY_NAME(formatted) column (D) from lowest to highest.
B5: 2. Apply the following filters: a) ASSIGNED TO (column B) to show your name only b) COMPLETED (column A) to show "N" only
B6: 3. Scroll over to Column E (Planned2021) and identify the first "Y" record. This indicates that the site was planned for inspection in 2020/2021. All planned sites should be addressed first; however do not filter this column because this may conceal other companies that should be grouoped with it and may have the same name.
B7: 4. Keeping #3 in mind, look through the values of COMPANY_NAME (formatted) and regulated entity name to identify groups of records that can be united under one legal name, (e.g. ‘NEWALTA’ and ‘NEWALTA CORPORATION’, or ‘CN RAIL’ and ‘CANADIAN NATIONAL RAILWAY’).
B8: 5. Use COMPANY_NAME (formatted) or regulated entity name to search for the company's legal name in the provincial and federal registries (the list of registry websites is available below). If the company name is not found in the provided registries, use Google to search by the company name (colummn D) as well as the site address (columns G - I) . Usually a legal name can be found at the bottom of a company website.
B9: 6. Based on the information discovered through the previous step, create a grouping of regulated entities by entering the official company name for all applicable records in the Consolidated...Name fields (Q - S).
B10: 7. Ensure that the selected group of records has the same regulated entity id (column O). Update this field if necessary, e.g: - IF the regulated entity id for 'CN RAIL' is 123; - AND the regulated entity id for ‘CANADIAN NATIONAL RAILWAY’ is 456; - AND your search reveals that the Consolidated Official Name for both records should be 'CANADIAN NATIONAL RAILWAY'; - THEN change the regulated entity id for 'CN RAIL' from 123 to 456 and enter 'CANADIAN NATIONAL RAILWAY' in column Q & R for both records.
A12: LIST OF BUSINESS REGISTRIES*
A13: Province/Territory | B13: URL | C13: Username | D13: Password
A14: (National) Canadian Companies Database | B14: https://www.canada.ca/en/services/business/research/directoriescanadiancompanies.html | C14: Free -Not required | D14: Free -Not required
A15: Newfoundland | B15: https://cado.eservices.gov.nl.ca/CADOInternet/Company/CompanyNameNumberSearch.aspx | C15: Free -Not required | D15: Free -Not required
A16: Prince Edward Island | B16: http://www.gov.pe.ca/corporations/index.php | C16: Free -Not required | D16: Free -Not required
A17: Nova Scotia | B17: https://rjsc.gov.ns.ca/rjsc/search/inquiry.do | C17: Free -Not required | D17: Free -Not required
A18: New Brunswick | B18: https://www.pxw2.snb.ca/card_online/Search/search.aspx | C18: TBD | D18: TBD
A19: Quebec | B19: http://www.registreentreprises.gouv.qc.ca/en/ | C19: Free -Not required | D19: Free -Not required
A20: Ontario | B20: http://www.carswelllegalsolutions.com/corporation-and-business-name-information/ | C20: TBD | D20: TBD
A21: Manitoba | B21: http://www.companiesoffice.gov.mb.ca/search_registry.html | C21: Free -Not required | D21: Free -Not required
A22: Saskatchewan | B22: https://corporateregistry.isc.ca/ | C22: DQWG | D22: Dqwg2017
A23: British Columbia | B23: https://www2.gov.bc.ca/gov/content/governments/organizational-structure/ministries-organizations/ministries/citizens-services/bc-registries-online-services | C23: TBD | D23: TBD
A24: Yukon Territory | B24: https://ycor-reey.gov.yk.ca/search | C24: Free -Not required | D24: Free -Not required
... A26: Nunavut | B26: http://nunavutlegalregistries.ca/cr_index_en.shtml | C26: TBD | D26: TBD
A27: *These sources are out-dated and some links may malfunction. If this occurs, the most reliable source is the national, Canadian Companies Database.

Sheet MATCHRESULTS
A1: COMPLETED | B1: ASSIGNED TO | C1: IIS_ID | D1: COMPANY_NAME (formatted) | E1: Planned2021 | F1: COMPANY_NAME | G1: COUNTRY_SUBDIVISION_CD | H1: CITY_TOWN_NAME_NM | I1: Address | J1: POSTAL_CODE_TXT | K1: FILE_STATUS_CD | L1: SOUNDEX (Name) | M1: Matching ID | N1: Fuzzy Match | O1: regulated entity id | P1: regulated entity name | Q1: Consolidated Common English Name | R1: Consolidated Common French Name | S1: Notes | T1: For Discussion
A2: =IF(OR(Q2<>"",R2<>""),"Y","N") -> Y | B2: WILFREDA EDWARD-DOLCY | C2: 23289 | D2: E FOCUS TECHNOLOGY CORP | E2: Y | F2: E-FOCUS TECHNOLOGY CORP. | G2: BC | H2: VANCOUVER | I2: 510 EAST KENT AVENUE SOUTH | J2: V5X4V6 | K2: ACTIVE | L2: E122 | M2: 23289 | N2: E FOCUS TECHNOLOGY CORP | O2: 23289E122 | P2: E FOCUS TECHNOLOGY CORP | Q2: E-FOCUS TECHNOLOGY CORP
A3: =IF(OR(Q3<>"",R3<>""),"Y","N") -> Y | B3: WILFREDA EDWARD-DOLCY | C3: 20284 | D3: E ONE MOLI ENERGY CANADA LTD | E3: N | F3: E-ONE MOLI ENERGY (CANADA) LTD | G3: BC | H3: MAPLE RIDGE | I3: 20000 STEWART CRES. | J3: V2X 9E7 | K3: ACTIVE | L3: E554 | M3: 20284 | N3: E ONE MOLI ENERGY CANADA LTD | O3: 20284E554 | P3: E ONE MOLI ENERGY CANADA LTD | Q3: E-ONE MOLI ENERGY (CANADA) LIMITED
A4: =IF(OR(Q4<>"",R4<>""),"Y","N") -> Y | B4: WILFREDA EDWARD-DOLCY | C4: 3052741 | D4: EGGR TRANSPORT | E4: N | F4: EGGR Transport | G4: QC | H4: L'ASSOMPTION | I4: 45 ARBOIT | J4: J5W4P3 | K4: ACTIVE | L4: E263 | M4: 3052741 | N4: EGGR TRANSPORT | O4: 3052741E263 | P4: EGGR TRANSPORT | R4: LES ENTREPRISES DE GESTION GEORGES & ROBERT INC.
A5: =IF(OR(Q5<>"",R5<>""),"Y","N") -> Y | B5: WILFREDA EDWARD-DOLCY | C5: 1795076 | D5: EHMAN VENTURES LTD | E5: N | F5: EHMAN VENTURES LTD. | G5: MB | H5: CORMORANT | I5: 0 GD | J5: R0B0G0 | K5: ACTIVE | L5: E551 | M5: 1795076 | N5: EHMAN VENTURES LTD | O5: 1795076E551 | P5: EHMAN VENTURES LTD | Q5: EHMAN VENTURES LTD.
A6: =IF(OR(Q6<>"",R6<>""),"Y","N") -> Y | B6: WILFREDA EDWARD-DOLCY | C6: 23024 | D6: EIDAM DIAGNOSTICS CORPORATION DERMAMED | E6: N | F6: EIDAM DIAGNOSTICS CORPORATION / DERMAMED | G6: BC | H6: RICHMOND | I6: 11120 HORSESHOE WAY UNIT 140 | J6: V7A5H7 | K6: ACTIVE | L6: E353 | M6: 23024 | N6: EIDAM DIAGNOSTICS CORPORATION DERMAMED | O6: 23024E353 | P6: EIDAM DIAGNOSTICS CORPORATION DERMAMED | Q6: DERMAMED PHARMACEUTICAL INC.
A7: =IF(OR(Q7<>"",R7<>""),"Y","N") -> Y | B7: WILFREDA EDWARD-DOLCY | C7: 6091 | D7: EIFCO INC | E7: Y | F7: EIFCO INC | G7: QC | H7: SAINT-LAURENT | I7: 9430 HENRI-BOURASSA | J7: H4S1N8 | K7: ACTIVE | L7: E125 | M7: 6091 | N7: EIFCO INC | O7: 6091E125 | P7: EIFCO INC | Q7: Electrowind Supply Inc
A8: =IF(OR(Q8<>"",R8<>""),"Y","N") -> Y | B8: WILFREDA EDWARD-DOLCY | C8: 1793841 | D8: EILERS TRUCKING INC | E8: N | F8: EILERS TRUCKING INC. | G8: SK | H8: REDVERS | I8: 828 PO | J8: S0C2H0 | K8: ACTIVE | L8: E462 | M8: 1793841 | N8: EILERS TRUCKING INC | O8: 1793841E462 | P8: EILERS TRUCKING INC | Q8: EILERS TRUCKING INC.
A9: =IF(OR(Q9<>"",R9<>""),"Y","N") -> Y | B9: WILFREDA EDWARD-DOLCY | C9: 4273 | D9: EKA CHIMIE CANADA INC | E9: Y | F9: EKA CHIMIE CANADA INC | G9: QC | H9: MAGOG | I9: 1900, RUE ST-PATRICE EST | J9: J1X 4X6 | K9: ACTIVE | L9: E225 | M9: 2613 | N9: EKA CHIMIE CANADA INC | O9: 2613E225 | P9: EKA CHIMIE CANADA INC | Q9: NOURYON CHEMICALS LTD.
A10: =IF(OR(Q10<>"",R10<>""),"Y","N") -> Y | B10: WILFREDA EDWARD-DOLCY | C10: 2613 | D10: EKA CHIMIE CANADA INC | E10: N | F10: EKA CHIMIE CANADA INC. | G10: QC | H10: SALABERRY-DE-VALLEYFIELD | I10: 640, RUE DES ERABLES | J10: J6T 6G4 | K10: ACTIVE | L10: E225 | M10: 2613 | N10: EKA CHIMIE CANADA INC | O10: 2613E225 | P10: EKA CHIMIE CANADA INC | Q10: NOURYON CHEMICALS LTD.
A11: =IF(OR(Q11<>"",R11<>""),"Y","N") -> Y | B11: WILFREDA EDWARD-DOLCY | C11: 12285 | D11: ELANCO ANIMAL HEALTH | E11: N | F11: ELANCO ANIMAL HEALTH | G11: ON | H11: GUELPH | I11: 150 RESEARCH LANE SUITE 120 | J11: N1G 4T2 | K11: ACTIVE | L11: E452 | M11: 12285 | N11: ELANCO ANIMAL HEALTH | O11: 12332E444 | P11: ELANCO ANIMAL HEALTH | Q11: ELI LILLY CANADA INC.
A12: =IF(OR(Q12<>"",R12<>""),"Y","N") -> Y | B12: WILFREDA EDWARD-DOLCY | C12: 12421 | D12: ELCAN OPTICAL TECHNOLOGIES | E12: N | F12: ELCAN OPTICAL TECHNOLOGIES | G12: ON | H12: MIDLAND | I12: 450 LEITZ ROAD (OFF ELLEN ROAD) | J12: L4R 5B8 | K12: ACTIVE | L12: E425 | M12: 12421 | N12: ELCAN OPTICAL TECHNOLOGIES | O12: 12421E425 | P12: ELCAN OPTICAL TECHNOLOGIES | Q12: Raytheon Canada Limited | R12: Raytheon Canada Limitée
A13: =IF(OR(Q13<>"",R13<>""),"Y","N") -> Y | B13: WILFREDA EDWARD-DOLCY | C13: 1034057 | D13: ELCANO EXPLORATION | E13: N | F13: Elcano Exploration | G13: AB | H13: CALGARY | I13: 550 6 | J13: T2P0S2 | K13: ACTIVE | L13: E425 | M13: 1034057 | N13: ELCANO EXPLORATION | O13: 1034057E425 | P13: ELCANO EXPLORATION | Q13: ELCANO EXPLORATION LTD.
A14: =IF(OR(Q14<>"",R14<>""),"Y","N") -> Y | B14: WILFREDA EDWARD-DOLCY | C14: 3905 | D14: ELCO LTD | E14: N | F14: ELCO LTD | G14: NS | H14: HALIFAX | I14: 61 RADDALL AVE BURNSIDE INDUSTRIAL PARK | J14: B3B 1T4 | K14: ACTIVE | L14: E424 | M14: 3905 | N14: ELCO LTD | O14: 3905E424 | P14: ELCO LTD | Q14: ELCO LTD.
A15: =IF(OR(Q15<>"",R15<>""),"Y","N") -> Y | B15: WILFREDA EDWARD-DOLCY | C15: 852 | D15: ELCO LTD | E15: N | F15: ELCO LTD. | G15: NB | H15: BATHURST | I15: 1805 VANIER BLVD. | J15: E2A 7B7 | K15: ACTIVE | L15: E424 | M15: 3905 | N15: ELCO LTD | O15: 3905E424 | P15: ELCO LTD | Q15: ELCO LTD.
A16: =IF(OR(Q16<>"",R16<>""),"Y","N") -> Y | B16: WILFREDA EDWARD-DOLCY | C16: 7633563 | D16: ELECTRIC BIKE BREWING COMPANY | E16: N | F16: Electric Bike Brewing Company | G16: BC | H16: VANCOUVER | I16: 20 4TH | J16: V5T1E8 | K16: ACTIVE | L16: E423 | M16: 7633563 | N16: ELECTRIC BIKE BREWING COMPANY | O16: 7633563E423 | P16: ELECTRIC BIKE BREWING COMPANY | Q16: ELECTRIC BICYCLE BREWING INC.
A17: =IF(OR(Q17<>"",R17<>""),"Y","N") -> Y | B17: WILFREDA EDWARD-DOLCY | C17: 20777 | D17: ELECTRIC INSULATION MATERIALS LTD | E17: N | F17: ELECTRIC INSULATION MATERIALS LTD. | G17: BC | H17: COQUITLAM | I17: 2423 CANOE STREET | J17: V3K 6A9 | K17: ACTIVE | L17: E423 | M17: 20777 | N17: ELECTRIC INSULATION MATERIALS LTD | O17: 20777E423 | P17: ELECTRIC INSULATION MATERIALS LTD | Q17: EIM Electric Insulation Materials (Vanc.) Ltd. | S17: not found in DB
A18: =IF(OR(Q18<>"",R18<>""),"Y","N") -> Y | B18: WILFREDA EDWARD-DOLCY | C18: 4112705 | D18: ELECTRIC MOTORCYCLES WINDSOR | E18: Y | F18: Electric Motorcycles Windsor | G18: ON | H18: WINDSOR | I18: 3143 WALKER | J18: N8W3R6 | K18: ACTIVE | L18: E423 | M18: 4112705 | N18: ELECTRIC MOTORCYCLES WINDSOR | O18: 4112705E423 | P18: ELECTRIC MOTORCYCLES WINDSOR | Q18: SOAR Hobby & more
A19: =IF(OR(Q19<>"",R19<>""),"Y","N") -> Y | B19: WILFREDA EDWARD-DOLCY | C19: 833 | D19: ELECTRICAL AND REFRIGERATION SRV LTD | E19: Y | F19: ELECTRICAL & REFRIGERATION SRV. LTD. | G19: NB | H19: MONCTON | I19: 88 BEAVERBROOK STREET P O BOX 2010, STATION A | J19: E1C 8N8 | K19: ACTIVE | L19: E423 | M19: 833 | N19: ELECTRICAL AND REFRIGERATION SRV LTD | O19: 833E423 | P19: ELECTRICAL AND REFRIGERATION SRV LTD | Q19: Charmichael Engineering
A20: =IF(OR(Q20<>"",R20<>""),"Y","N") -> Y | B20: WILFREDA EDWARD-DOLCY | C20: 12288 | D20: ELECTRICAL CONTACTS LIMITED | E20: Y | F20: ELECTRICAL CONTACTS LIMITED. | G20: ON | H20: HANOVER | I20: 519-22ND. AVE. | J20: N4N 3C4 | K20: ACTIVE | L20: E423 | M20: 12288 | N20: ELECTRICAL CONTACTS LIMITED | O20: 12288E423 | P20: ELECTRICAL CONTACTS LIMITED | Q20: ELECTRICAL CONTACTS LIMITED
A21: =IF(OR(Q21<>"",R21<>""),"Y","N") -> Y | B21: WILFREDA EDWARD-DOLCY | C21: 767 | D21: ELECTRO MECHANICAL SRV LTD | E21: Y | F21: ELECTRO MECHANICAL SRV. LTD. | G21: NL | H21: MOUNT PEARL | I21: 92 GLENCOE AVE DONOVANS INDUSTRIAL PARK | J21: A1N 4S9 | K21: ACTIVE | L21: E423 | M21: 767 | N21: ELECTRO MECHANICAL SRV LTD | O21: 767E423 | P21: ELECTRO MECHANICAL SRV LTD | Q21: ELECTRO MECHANICAL SERVICES
A22: =IF(OR(Q22<>"",R22<>""),"Y","N") -> Y | B22: WILFREDA EDWARD-DOLCY | C22: 2532759 | D22: ELECTRO SONIC | E22: N | F22: Electro Sonic | G22: BC | H22: BURNABY | I22: 5489 BYRNE 173 | J22: V5J3J1 | K22: ACTIVE | L22: E423 | M22: 2532759 | N22: ELECTRO SONIC | O22: 2532759E423 | P22: ELECTRO SONIC | Q22: ELECTRO SONIC GROUP, INC.
A23: =IF(OR(Q23<>"",R23<>""),"Y","N") -> Y | B23: WILFREDA EDWARD-DOLCY | C23: 12308 | D23: ELECTRO SONIC INC | E23: N | F23: ELECTRO SONIC INC. | G23: ON | H23: WILLOWDALE | I23: 1100 GORDON BAKER RD. | J23: M2H 3B3 | K23: ACTIVE | L23: E423 | M23: 2532759 | N23: ELECTRO SONIC | O23: 2532759E423 | P23: ELECTRO SONIC | Q23: ELECTRO SONIC GROUP, INC.
A24: =IF(OR(Q24<>"",R24<>""),"Y","N") -> Y | B24: WILFREDA EDWARD-DOLCY | C24: 13828 | D24: ELECTRO WIND SUPPLY INC | E24: N | F24: ELECTRO-WIND SUPPLY INC. | G24: ON | H24: GUELPH | I24: 2 TAGGART CRT P.O. BOX 713 | J24: N1H 6L3 | K24: ACTIVE | L24: E423 | M24: 13828 | N24: ELECTRO WIND SUPPLY INC | O24: 13828E423 | P24: ELECTRO WIND SUPPLY INC | Q24: ELECTRO-WIND SUPPLY INC.
A25: =IF(OR(Q25<>"",R25<>""),"Y","N") -> Y | B25: WILFREDA EDWARD-DOLCY | C25: 12310 | D25: ELECTRONIC CRAFTSMEN LTD | E25: N | F25: ELECTRONIC CRAFTSMEN LTD. | G25: ON | H25: WATERLOO | I25: 73 SCHAEFER | J25: N2L4C4 | K25: ACTIVE | L25: E423 | M25: 12310 | N25: ELECTRONIC CRAFTSMEN LTD | O25: 12310E423 | P25: ELECTRONIC CRAFTSMEN LTD | Q25: E CRAFTSMEN CORPORATION
A26: =IF(OR(Q26<>"",R26<>""),"Y","N") -> Y | B26: WILFREDA EDWARD-DOLCY | C26: 6733067 | D26: ELECTRONIC RECYCLING ASSOCIATION | E26: N | F26: Electronic Recycling Association | G26: AB | H26: CALGARY | I26: 1301 34 | J26: T2G1V8 | K26: ACTIVE | L26: E423 | M26: 6733067 | N26: ELECTRONIC RECYCLING ASSOCIATION | O26: 6733067E423 | P26: ELECTRONIC RECYCLING ASSOCIATION | Q26: The Electronic Recycling Association of Alberta
A27: =IF(OR(Q27<>"",R27<>""),"Y","N") -> Y | B27: WILFREDA EDWARD-DOLCY | C27: 4112704 | D27: ELECTROVAYA INC | E27: N | F27: Electrovaya Inc. | G27: ON | H27: MISSISSAUGA | I27: 2645 ROYAL WINDSOR | J27: L5J1K9 | K27: ACTIVE | L27: E423 | M27: 4112704 | N27: ELECTROVAYA INC | O27: 4112704E423 | P27: ELECTROVAYA INC | Q27: ELECTROVAYA INC.
A28: =IF(OR(Q28<>"",R28<>""),"Y","N") -> Y | B28: WILFREDA EDWARD-DOLCY | C28: 3732606 | D28: ELEMENT | E28: N | F28: Element | G28: ON | H28: CAMBRIDGE | I28: 15 HIGH RIDGE | J28: N1R7L3 | K28: ACTIVE | L28: E455 | M28: 3732606 | N28: ELEMENT | O28: 3732606E455 | P28: ELEMENT | Q28: ELEMENT MATERIALS TECHNOLOGY CANADA INC.
A29: =IF(OR(Q29<>"",R29<>""),"Y","N") -> Y | B29: WILFREDA EDWARD-DOLCY | C29: 2773357 | D29: ELEY AIR SERVICE LTD | E29: N | F29: Eley Air Service Ltd | G29: SK | H29: COLONSAY | I29: 411 PO | J29: S0K0Z0 | K29: ACTIVE | L29: E462 | M29: 2773357 | N29: ELEY AIR SERVICE LTD | O29: 2773357E462 | P29: ELEY AIR SERVICE LTD | Q29: ELEY AIR SERVICE LTD.
A30: =IF(OR(Q30<>"",R30<>""),"Y","N") -> Y | B30: WILFREDA EDWARD-DOLCY | C30: 13783 | D30: ELGIN FIRE EXTINGUISHERS | E30: N | F30: ELGIN FIRE EXTINGUISHERS | G30: ON | H30: ST THOMAS | I30: 45123 ELM | J30: N5P3S6 | K30: ACTIVE | L30: E425 | M30: 13783 | N30: ELGIN FIRE EXTINGUISHERS | O30: 13783E425 | P30: ELGIN FIRE EXTINGUISHERS | Q30: ELGIN FIRE EXTINGUISHERS | S30: not found in DB
A31: =IF(OR(Q31<>"",R31<>""),"Y","N") -> Y | B31: WILFREDA EDWARD-DOLCY | C31: 13807 | D31: ELGIN MOTOR FREIGHT INC | E31: N | F31: ELGIN MOTOR FREIGHT INC. | G31: ON | H31: LONDON | I31: 1497 WILTON GROVE ROAD | J31: N6N 1M3 | K31: ACTIVE | L31: E425 | M31: 13807 | N31: ELGIN MOTOR FREIGHT INC | O31: 13807E425 | P31: ELGIN MOTOR FREIGHT INC | Q31: ELGIN MOTOR FREIGHT INC.
A32: =IF(OR(Q32<>"",R32<>""),"Y","N") -> Y | B32: WILFREDA EDWARD-DOLCY | C32: 12332 | D32: ELI LILLY CANADA INC | E32: Y | F32: ELI LILLY CANADA INC. | G32: ON | H32: SCARBOROUGH | I32: 3650 DANFORTH AVE. | J32: M1N 2E8 | K32: ACTIVE | L32: E444 | M32: 12332 | N32: ELI LILLY CANADA INC | O32: 12332E444 | P32: ELI LILLY CANADA INC | Q32: ELI LILLY CANADA INC
A33: =IF(OR(Q33<>"",R33<>""),"Y","N") -> Y | B33: WILFREDA EDWARD-DOLCY | C33: 1773107 | D33: ELIAS WOODWORK | E33: N | F33: Elias Woodwork | G33: MB | H33: WINKLER | I33: 1659 PO | J33: R6W4B5 | K33: ACTIVE | L33: E423 | M33: 1773107 | N33: ELIAS WOODWORK | O33: 1773107E423 | P33: ELIAS WOODWORK | Q33: ELIAS WOODWORKING AND MANUFACTURING LTD.
A34: =IF(OR(Q34<>"",R34<>""),"Y","N") -> Y | B34: WILFREDA EDWARD-DOLCY | C34: 15796 | D34: ELIRPA COSTRUCTION AND MATERIALS LIMITED | E34: N | F34: ELIRPA COSTRUCTION & MATERIALS LIMITED | G34: ON | H34: PICKERING | I34: P.O. BOX 187 2890 BROCK ROAD | J34: L1V 2R4 | K34: ACTIVE | L34: E461 | M34: 15796 | N34: ELIRPA COSTRUCTION AND MATERIALS LIMITED | O34: 15796E461 | P34: ELIRPA COSTRUCTION AND MATERIALS LIMITED | Q34: ELIRPA CONSTRUCTION & MATERIALS LIMITED
A35: =IF(OR(Q35<>"",R35<>""),"Y","N") -> Y | B35: WILFREDA EDWARD-DOLCY | C35: 9970 | D35: ELITE AUTOBODY | E35: Y | F35: ELITE AUTOBODY | G35: SK | H35: REGINA | I35: 240 HODSMAN ROAD | J35: S4N 5X4 | K35: ACTIVE | L35: E433 | M35: 9970 | N35: ELITE AUTOBODY | O35: 9970E433 | P35: ELITE AUTOBODY | Q35: ELITE AUTO BODY LTD.
A36: =IF(OR(Q36<>"",R36<>""),"Y","N") -> Y | B36: WILFREDA EDWARD-DOLCY | C36: 20966 | D36: ELITE FIRE PROTECTION LTD | E36: N | F36: ELITE FIRE PROTECTION LTD. | G36: BC | H36: ABBOTSFORD | I36: UNIT 1 - 33605 MCCLURE ROAD | J36: V2S 7W2 | K36: ACTIVE | L36: E431 | M36: 20966 | N36: ELITE FIRE PROTECTION LTD | O36: 20966E431 | P36: ELITE FIRE PROTECTION LTD | Q36: ELITE FIRE PROTECTION LTD.
A37: =IF(OR(Q37<>"",R37<>""),"Y","N") -> Y | B37: WILFREDA EDWARD-DOLCY | C37: 3254 | D37: ELITE FLEET | E37: N | F37: ELITE FLEET | G37: NB | H37: MONCTON | I37: 106 CALEDONIA ROD | J37: E1H 3C6 | K37: ACTIVE | L37: E431 | M37: 3254 | N37: ELITE FLEET | O37: 3254E431 | P37: ELITE FLEET | Q37: EASSONS TRANSPORT LIMITED
A38: =IF(OR(Q38<>"",R38<>""),"Y","N") -> Y | B38: WILFREDA EDWARD-DOLCY | C38: 2454933 | D38: ELITEMED INC | E38: N | F38: EliteMed Inc | G38: ON | H38: MISSISSAUGA | I38: 3190 RIDGEWAY 20 | J38: L5L5S8 | K38: ACTIVE | L38: E435 | M38: 2454933 | N38: ELITEMED INC | O38: 2454933E435 | P38: ELITEMED INC | Q38: ELITEMED INC.
A39: =IF(OR(Q39<>"",R39<>""),"Y","N") -> Y | B39: WILFREDA EDWARD-DOLCY | C39: 22365 | D39: ELK VALLEY COAL GREEN HILLS OPERATION | E39: N | F39: ELK VALLEY COAL [GREEN HILLS OPERATION] | G39: BC | H39: ELKFORD | I39: 6 KM NORTH OF ELKFORD | J39: VOB 1H0 | K39: ACTIVE | L39: E421 | M39: 22365 | N39: ELK VALLEY COAL GREEN HILLS OPERATION | O39: 22365E421 | P39: ELK VALLEY COAL GREEN HILLS OPERATION | Q39: ELK VALLEY COAL [GREEN HILLS OPERATION / POSCO Canada Limited]
A40: =IF(OR(Q40<>"",R40<>""),"Y","N") -> Y | B40: WILFREDA EDWARD-DOLCY | C40: 6236 | D40: ELKEM METAL CANADA INC | E40: N | F40: ELKEM MÉTAL CANADA INC. | G40: QC | H40: CHICOUTIMI | I40: 2020 DE LA RÉSERVE | J40: G7J0E1 | K40: ACTIVE | L40: E425 | M40: 6236 | N40: ELKEM METAL CANADA INC | O40: 6236E425 | P40: ELKEM METAL CANADA INC | Q40: ELKEM MÉTAL CANADA INC.
A41: =IF(OR(Q41<>"",R41<>""),"Y","N") -> Y | B41: WILFREDA EDWARD-DOLCY | C41: 12350 | D41: ELLWOOD ROBINSON LTD | E41: N | F41: ELLWOOD ROBINSON LTD. | G41: ON | H41: SAULT STE. MARIE | I41: 2075 GREAT NORTHERN RD. P.O. BOX 40 | J41: P6A 5L2 | K41: ACTIVE | L41: E436 | M41: 12350 | N41: ELLWOOD ROBINSON LTD | O41: 12350E436 | P41: ELLWOOD ROBINSON LTD | Q41: ELLWOOD ROBINSON INC.
A42: =IF(OR(Q42<>"",R42<>""),"Y","N") -> Y | B42: WILFREDA EDWARD-DOLCY | C42: 16980 | D42: ELM CREEK COOPERATIVE OIL AND SUPPLIES LTD | E42: Y | F42: ELM CREEK COOPERATIVE OIL & SUPPLIES LTD. | G42: MB | H42: ELM CREEK | I42: 43 CHURCH AVENUE | J42: R0G 0N0 | K42: ACTIVE | L42: E452 | M42: 16980 | N42: ELM CREEK COOPERATIVE OIL AND SUPPLIES LTD | O42: 8293F363 | P42: ELM CREEK COOPERATIVE OIL AND SUPPLIES LTD | Q42: FEDERATED CO-OPERATIVES LIMITED | S42: not found in DB
A43: =IF(OR(Q43<>"",R43<>""),"Y","N") -> Y | B43: WILFREDA EDWARD-DOLCY | C43: 3159 | D43: ELM RIVER RV PARK LTD | E43: Y | F43: ELM RIVER RV PARK LTD | G43: NS | H43: DEBERT | I43: 3807 HYWAY #4 RR #1 | J43: B0M 1G0 | K43: ACTIVE | L43: E456 | M43: 3159 | N43: ELM RIVER RV PARK LTD | O43: 3159E456 | P43: ELM RIVER RV PARK LTD | Q43: ELM RIVER RV PARK LIMITED
A44: =IF(OR(Q44<>"",R44<>""),"Y","N") -> Y | B44: WILFREDA EDWARD-DOLCY | C44: 246 | D44: ELM TREE RESOURCES LTD | E44: N | F44: ELM TREE RESOURCES LTD. | G44: NB | H44: BATHURST | I44: 1370 JOHNSON AVENUE | J44: E2A 3T7 | K44: ACTIVE | L44: E453 | M44: 246 | N44: ELM TREE RESOURCES LTD | O44: 246E453 | P44: ELM TREE RESOURCES LTD | Q44: ELMTREE RESOURCES LTD.
A45: =IF(OR(Q45<>"",R45<>""),"Y","N") -> Y | B45: WILFREDA EDWARD-DOLCY | C45: 11750 | D45: ELMIRA PET PRODUCTS LIMITED | E45: N | F45: ELMIRA PET PRODUCTS LIMITED | G45: ON | H45: ELMIRA | I45: 35 MARTIN'S LANE P.O. BOX 100 | J45: N3B 2Z5 | K45: ACTIVE | L45: E456 | M45: 11750 | N45: ELMIRA PET PRODUCTS LIMITED | O45: 11750E456 | P45: ELMIRA PET PRODUCTS LIMITED | Q45: ELMIRA PET PRODUCTS LTD.
A46: =IF(OR(Q46<>"",R46<>""),"Y","N") -> Y | B46: WILFREDA EDWARD-DOLCY | C46: 1713262 | D46: ELT AVIATION INC | E46: N | F46: ELT AVIATION INC. | G46: BC | H46: CRANBROOK | I46: 9426 AIRPORT ACCESS | J46: V1C7E4 | K46: ACTIVE | L46: E431 | M46: 1713262 | N46: ELT AVIATION INC | O46: 1713262E431 | P46: ELT AVIATION INC | Q46: ELT AVIATION LTD.
A47: =IF(OR(Q47<>"",R47<>""),"Y","N") -> Y | B47: WILFREDA EDWARD-DOLCY | C47: 6432985 | D47: EM AND I | E47: N | F47: EM & I | G47: NS | H47: DARTMOUTH | I47: 10 THORNHILL 3 | J47: B3B1S1 | K47: ACTIVE | L47: E553 | M47: 6432985 | N47: EM AND I | O47: 6432985E553 | P47: EM AND I | Q47: EM & I (CANADA) LTD.
A48: =IF(OR(Q48<>"",R48<>""),"Y","N") -> Y | B48: WILFREDA EDWARD-DOLCY | C48: 16982 | D48: EM PLASTIC AND ELECTRIC PRODUCTS | E48: N | F48: EM PLASTIC & ELECTRIC PRODUCTS | G48: MB | H48: WINNIPEG | I48: 211 SHEPPARD STREET | J48: R2X 3A1 | K48: ACTIVE | L48: E514 | M48: 16982 | N48: EM PLASTIC AND ELECTRIC PRODUCTS | O48: 16982E514 | P48: EM PLASTIC AND ELECTRIC PRODUCTS | Q48: EM PLASTIC & ELECTRIC PRODUCTS LIMITED | R48: PRODUITS PLASTIQUE ET MATERIEL ELECTRIQUE EM LTEE
A49: =IF(OR(Q49<>"",R49<>""),"Y","N") -> Y | B49: WILFREDA EDWARD-DOLCY | C49: 4587 | D49: EMBALLAGE ROUVILLE INC | E49: N | F49: EMBALLAGE ROUVILLE INC | G49: QC | H49: MARIEVILLE | I49: 400, HENRI-BOURASSA | J49: J3M 1R9 | K49: ACTIVE | L49: E514 | M49: 4587 | N49: EMBALLAGE ROUVILLE INC | O49: 4587E514 | P49: EMBALLAGE ROUVILLE INC | Q49: Gelpac bags inc. | R49: Gelpac sacs inc.
A50: =IF(OR(Q50<>"",R50<>""),"Y","N") -> Y | B50: WILFREDA EDWARD-DOLCY | C50: 5939 | D50: EMBALLAGES DOMTAR DIVISION DU RECYCLAGE R | E50: N | F50: EMBALLAGES DOMTAR/DIVISION DU RECYCLAGE R | G50: QC | H50: MONTREAL-EST | I50: 11445 RIVET | J50: H1B1A9 | K50: ACTIVE | L50: E514 | M50: 5939 | N50: EMBALLAGES DOMTAR DIVISION DU RECYCLAGE R | O50: 5939E514 | P50: EMBALLAGES DOMTAR DIVISION DU RECYCLAGE R | Q50: DOMTAR INC.
A51: =IF(OR(Q51<>"",R51<>""),"Y","N") -> Y | B51: WILFREDA EDWARD-DOLCY | C51: 7165 | D51: EMBALLAGES JEAN CARTIER INC | E51: Y | F51: EMBALLAGES JEAN CARTIER INC | G51: QC | H51: SAINT-CESAIRE | I51: 2325 INDUSTRIEL | J51: J0L1T0 | K51: ACTIVE | L51: E514 | M51: 7165 | N51: EMBALLAGES JEAN CARTIER INC | O51: 7165E514 | P51: EMBALLAGES JEAN CARTIER INC | Q51: JEAN CARTIER PACKAGING INC. | R51: EMBALLAGES JEAN CARTIER INC.
A52: =IF(OR(Q52<>"",R52<>""),"Y","N") -> Y | B52: WILFREDA EDWARD-DOLCY | C52: 6018 | D52: EMBALLAGES KNOWLTON INC LES | E52: Y | F52: EMBALLAGES KNOWLTON INC, LES | G52: QC | H52: LAC-BROME | I52: 315, CHEMIN KNOWLTON, C.P. 190 | J52: J0E 1V0 | K52: ACTIVE | L52: E514 | M52: 6018 | N52: EMBALLAGES KNOWLTON INC LES | O52: 6018E514 | P52: EMBALLAGES KNOWLTON INC LES | Q52: KNOWLTON PACKAGING INC. | R52: LES EMBALLAGES KNOWLTON INC.
A53: =IF(OR(Q53<>"",R53<>""),"Y","N") -> Y | B53: WILFREDA EDWARD-DOLCY | C53: 5618 | D53: EMBALLAGES MASKA INC | E53: N | F53: EMBALLAGES MASKA INC | G53: QC | H53: SAINT-HYACINTHE | I53: 7450, AVENUE PION | J53: J2R 1R9 | K53: ACTIVE | L53: E514 | M53: 5618 | N53: EMBALLAGES MASKA INC | O53: 5618E514 | P53: EMBALLAGES MASKA INC | R53: EMBALLAGES MASKA INC.
A54: =IF(OR(Q54<>"",R54<>""),"Y","N") -> Y | B54: WILFREDA EDWARD-DOLCY | C54: 3792595 | D54: EMBASSY INGREDIENTS LTD | E54: N | F54: Embassy Ingredients Ltd. | G54: ON | H54: BRAMPTON | I54: 5 INTERMODAL 1 | J54: L6T5V9 | K54: ACTIVE | L54: E512 | M54: 3792595 | N54: EMBASSY INGREDIENTS LTD | O54: 3792595E512 | P54: EMBASSY INGREDIENTS LTD | Q54: EMBASSY INGREDIENTS LTD.
A55: =IF(OR(Q55<>"",R55<>""),"Y","N") -> Y | B55: WILFREDA EDWARD-DOLCY | C55: 1726 | D55: EMBERLEYS TRANSPORT LTD | E55: N | F55: EMBERLEY'S TRANSPORT LTD. | G55: NL | H55: MARYSTOWN | I55: BOX 200 MCGETTIGAN BLVD | J55: A0E 2M0 | K55: ACTIVE | L55: E516 | M55: 736 | N55: EMBERLEYS TRANSPORT LTD | O55: 736E516 | P55: EMBERLEYS TRANSPORT LTD | Q55: EMBERLEY'S TRANSPORT LIMITED
A56: =IF(OR(Q56<>"",R56<>""),"Y","N") -> Y | B56: WILFREDA EDWARD-DOLCY | C56: 736 | D56: EMBERLEYS TRANSPORT LTD | E56: N | F56: EMBERLEY'S TRANSPORT LTD. | G56: NL | H56: MOUNT PEARL | I56: 118 GLENCOE | J56: A1N 4S9 | K56: ACTIVE | L56: E516 | M56: 736 | N56: EMBERLEYS TRANSPORT LTD | O56: 736E516 | P56: EMBERLEYS TRANSPORT LTD | Q56: EMBERLEY'S TRANSPORT LIMITED
A57: =IF(OR(Q57<>"",R57<>""),"Y","N") -> Y | B57: WILFREDA EDWARD-DOLCY | C57: 12352 | D57: EMBURY COMPANY | E57: N | F57: EMBURY COMPANY | G57: ON | H57: ORILLIA | I57: 1 INDUSTRIAL RD. | J57: L3V 6K7 | K57: ACTIVE | L57: E516 | M57: 12352 | N57: EMBURY COMPANY | O57: 12352E516 | P57: EMBURY COMPANY | Q57: EMBURY COMPANY | S57: not found in DB
A58: =IF(OR(Q58<>"",R58<>""),"Y","N") -> Y | B58: WILFREDA EDWARD-DOLCY | C58: 19247 | D58: EMCO CORPORATION | E58: N | F58: EMCO CORPORATION | G58: MB | H58: WINNIPEG | I58: 1-717 LAGIMODIERE BLVD | J58: R2J 3X2 | K58: ACTIVE | L58: E522 | M58: 19980 | N58: EMCO CORPORATION | O58: 14468E522 | P58: EMCO CORPORATION | Q58: EMCO CORPORATION
A59: =IF(OR(Q59<>"",R59<>""),"Y","N") -> Y | B59: WILFREDA EDWARD-DOLCY | C59: 16531 | D59: EMCO CORPORATION | E59: N | F59: EMCO CORPORATION | G59: ON | H59: HAMILTON | I59: 1660 UPPER OTTAWA STREET | J59: L8W 3P2 | K59: ACTIVE | L59: E522 | M59: 19980 | N59: EMCO CORPORATION | O59: 14468E522 | P59: EMCO CORPORATION | Q59: EMCO CORPORATION
A60: =IF(OR(Q60<>"",R60<>""),"Y","N") -> Y | B60: WILFREDA EDWARD-DOLCY | C60: 18157 | D60: EMCO CORPORATION | E60: N | F60: EMCO CORPORATION | G60: MB | H60: WINNIPEG | I60: 1336 SARGENT AVE. | J60: R3E 0G4 | K60: ACTIVE | L60: E522 | M60: 19980 | N60: EMCO CORPORATION | O60: 14468E522 | P60: EMCO CORPORATION | Q60: EMCO CORPORATION
A61: =IF(OR(Q61<>"",R61<>""),"Y","N") -> Y | B61: WILFREDA EDWARD-DOLCY | C61: 19980 | D61: EMCO CORPORATION | E61: N | F61: EMCO CORPORATION | G61: BC | H61: LANGLEY | I61: UNIT 101 - 20577 LANGELY BYPASS N59 06.845 BY W122 39.153 | J61: V3A 5E8 | K61: ACTIVE | L61: E522 | M61: 19980 | N61: EMCO CORPORATION | O61: 14468E522 | P61: EMCO CORPORATION | Q61: EMCO CORPORATION
A62: =IF(OR(Q62<>"",R62<>""),"Y","N") -> Y | B62: WILFREDA EDWARD-DOLCY | C62: 9431 | D62: EMCO LIMITED FRONTIER MINING DIVISION | E62: N | F62: EMCO LIMITED - FRONTIER MINING DIVISION | G62: NT | H62: YELLOWKNIFE | I62: 327A OLD AIRPORT ROAD | J62: X1A 3T3 | K62: ACTIVE | L62: E524 | M62: 9431 | N62: EMCO LIMITED FRONTIER MINING DIVISION | O62: 14468E522 | P62: EMCO LIMITED FRONTIER MINING DIVISION | Q62: EMCO CORPORATION
A63: =IF(OR(Q63<>"",R63<>""),"Y","N") -> Y | B63: WILFREDA EDWARD-DOLCY | C63: 5415 | D63: EMCO MACHINERIE AND LOCATION INC | E63: Y | F63: EMCO MACHINERIE & LOCATION INC | G63: QC | H63: MONTREAL | I63: 6659 DU PARC | J63: H2V4J1 | K63: ACTIVE | L63: E525 | M63: 5415 | N63: EMCO MACHINERIE AND LOCATION INC | O63: 5415E525 | P63: EMCO MACHINERIE AND LOCATION INC | R63: EMCO MACHINERIE ET LOCATION INC.
A64: =IF(OR(Q64<>"",R64<>""),"Y","N") -> Y | B64: WILFREDA EDWARD-DOLCY | C64: 14468 | D64: EMCO SUPPLY | E64: N | F64: EMCO SUPPLY | G64: ON | H64: NORTH BAY | I64: 300 FEE STREET | J64: P1B 8G5 | K64: ACTIVE | L64: E522 | M64: 14468 | N64: EMCO SUPPLY | O64: 14468E522 | P64: EMCO SUPPLY | Q64: EMCO CORPORATION
A65: =IF(OR(Q65<>"",R65<>""),"Y","N") -> Y | B65: WILFREDA EDWARD-DOLCY | C65: 16772 | D65: EMCO SUPPLY FIRE PROTECTION DIVISION | E65: N | F65: EMCO SUPPLY, FIRE PROTECTION DIVISION | G65: ON | H65: WESTON | I65: 65 HUXLEY | J65: M9M 1H5 | K65: ACTIVE | L65: E522 | M65: 16772 | N65: EMCO SUPPLY FIRE PROTECTION DIVISION | O65: 14468E522 | P65: EMCO SUPPLY FIRE PROTECTION DIVISION | Q65: EMCO CORPORATION
A66: =IF(OR(Q66<>"",R66<>""),"Y","N") -> Y | B66: WILFREDA EDWARD-DOLCY | C66: 20796 | D66: EMCO SUPPLY LTD | E66: Y | F66: EMCO SUPPLY LTD. | G66: BC | H66: PRINCE GEORGE | I66: 1596 QUINN ST S WEST PRINCE GEORGE | J66: V2N 1X4 | K66: ACTIVE | L66: E522 | M66: 14468 | N66: EMCO SUPPLY | O66: 14468E522 | P66: EMCO SUPPLY | Q66: EMCO CORPORATION
A67: =IF(OR(Q67<>"",R67<>""),"Y","N") -> Y | B67: WILFREDA EDWARD-DOLCY | C67: 22091 | D67: EMCO SUPPLY LTD | E67: N | F67: EMCO SUPPLY LTD. | G67: BC | H67: CRANBROOK | I67: 756 INDUSTRIAL RD #2 | J67: V1C 4C8 | K67: ACTIVE | L67: E522 | M67: 14468 | N67: EMCO SUPPLY | O67: 14468E522 | P67: EMCO SUPPLY | Q67: EMCO CORPORATION
A68: =IF(OR(Q68<>"",R68<>""),"Y","N") -> Y | B68: WILFREDA EDWARD-DOLCY | C68: 2433102 | D68: EMERALD COATINGS CASWELL CANADA | E68: N | F68: Emerald Coatings/Caswell Canada | G68: ON | H68: PALMERSTON | I68: 5914 WELLINGTON RD 123 | J68: N0G2P0 | K68: ACTIVE | L68: E564 | M68: 2433102 | N68: EMERALD COATINGS CASWELL CANADA | O68: 2433102E564 | P68: EMERALD COATINGS CASWELL CANADA | Q68: EMERALD COATINGS
A69: =IF(OR(Q69<>"",R69<>""),"Y","N") -> Y | B69: WILFREDA EDWARD-DOLCY | C69: 9864 | D69: EMERALD INDUSTRIES LTD | E69: N | F69: EMERALD INDUSTRIES LTD | G69: SK | H69: REGINA | I69: 1330 ELLIOTT ST | J69: S4N 3G3 | K69: ACTIVE | L69: E564 | M69: 9864 | N69: EMERALD INDUSTRIES LTD | O69: 9864E564 | P69: EMERALD INDUSTRIES LTD | Q69: EMERALD INDUSTRIES LTD.
A70: =IF(OR(Q70<>"",R70<>""),"Y","N") -> Y | B70: WILFREDA EDWARD-DOLCY | C70: 1692825 | D70: EMERGENCY HEALTH SERVICES LIFE FLIGHT | E70: N | F70: Emergency Health Services Life Flight | G70: NS | H70: GOFFS | I70: 637 BARNES | J70: B2T1K3 | K70: ACTIVE | L70: E562 | M70: 1692825 | N70: EMERGENCY HEALTH SERVICES LIFE FLIGHT | O70: 1692825E562 | P70: EMERGENCY HEALTH SERVICES LIFE FLIGHT | Q70: EMC EMERGENCY MEDICAL CARE INCORPORATED
A71: =IF(OR(Q71<>"",R71<>""),"Y","N") -> Y | B71: WILFREDA EDWARD-DOLCY | C71: 22614 | D71: EMERGENCY REFRIGERATION SERVICES INC | E71: N | F71: EMERGENCY REFRIGERATION SERVICES INC. | G71: AB | H71: CAMROSE | I71: BOX 1266 | J71: T4V 1X2 | K71: ACTIVE | L71: E562 | M71: 22614 | N71: EMERGENCY REFRIGERATION SERVICES INC | O71: 22614E562 | P71: EMERGENCY REFRIGERATION SERVICES INC | Q71: EMERGENCY REFRIGERATION INC.
A72: =IF(OR(Q72<>"",R72<>""),"Y","N") -> Y | B72: WILFREDA EDWARD-DOLCY | C72: 1053904 | D72: EMERGENT BIOSOLUTIONS | E72: N | F72: EMERGENT BIOSOLUTIONS | G72: MB | H72: WINNIPEG | I72: 155 INNOVATION | J72: R3T5Y3 | K72: ACTIVE | L72: E562 | M72: 1053904 | N72: EMERGENT BIOSOLUTIONS | O72: 1053904E562 | P72: EMERGENT BIOSOLUTIONS | Q72: Emergent BioSolutions Canada Inc.
A73: =IF(OR(Q73<>"",R73<>""),"Y","N") -> Y | B73: WILFREDA EDWARD-DOLCY | C73: 793317 | D73: EMERSON ELECTRIC CANADA LTD | E73: N | F73: EMERSON ELECTRIC CANADA LTD | G73: ON | H73: RICHMOND HILL | I73: 66 LEEK | J73: L4B1H1 | K73: ACTIVE | L73: E562 | M73: 793317 | N73: EMERSON ELECTRIC CANADA LTD | O73: 793317E562 | P73: EMERSON ELECTRIC CANADA LTD | Q73: EMERSON ELECTRIC CANADA LIMITED | R73: EMERSON ELECTRIQUE DU CANADA LIMITEE
A74: =IF(OR(Q74<>"",R74<>""),"Y","N") -> Y | B74: WILFREDA EDWARD-DOLCY | C74: 21089 | D74: EMIL ANDERSON CONSTRUCTION EAC INC | E74: N | F74: EMIL ANDERSON CONSTRUCTION (EAC) INC. | G74: BC | H74: HOPE | I74: 1313 - SIXTH AVENUE N49.37419 BY W121.42702 | J74: V0X 1L4 | K74: ACTIVE | L74: E545 | M74: 21089 | N74: EMIL ANDERSON CONSTRUCTION EAC INC | O74: 21089E545 | P74: EMIL ANDERSON CONSTRUCTION EAC INC | Q74: EMIL ANDERSON CONSTRUCTION (EAC) INC.
A75: =IF(OR(Q75<>"",R75<>""),"Y","N") -> Y | B75: WILFREDA EDWARD-DOLCY | C75: 152907 | D75: EMIRATES AUTO EXPORT AND IMPORT | E75: N | F75: Emirates Auto Export And Import | G75: BC | H75: NEW WESTMINSTER | I75: 320 EWEN | J75: V3M5B1 | K75: ACTIVE | L75: E563 | M75: 152907 | N75: EMIRATES AUTO EXPORT AND IMPORT | O75: 152907E563 | P75: EMIRATES AUTO EXPORT AND IMPORT | Q75: EMIRATES AUTO EXPORT & IMPORT LTD.
A76: =IF(OR(Q76<>"",R76<>""),"Y","N") -> Y | B76: WILFREDA EDWARD-DOLCY | C76: 9729 | D76: EMKES AUTO AND AG SUPPLIES | E76: Y | F76: EMKE'S AUTO & AG SUPPLIES | G76: SK | H76: GRENFELL | I76: 818 DESMOND ST | J76: S0G 2B0 | K76: ACTIVE | L76: E522 | M76: 9729 | N76: EMKES AUTO AND AG SUPPLIES | O76: 9729E522 | P76: EMKES AUTO AND AG SUPPLIES | Q76: EMKE'S AUTOMOTIVE SUPPLIES LTD | S76: not found in DB
A77: =IF(OR(Q77<>"",R77<>""),"Y","N") -> Y | B77: WILFREDA EDWARD-DOLCY | C77: 3313254 | D77: EMMERSON PACKAGING | E77: N | F77: EMMERSON PACKAGING | G77: ON | H77: BELLEVILLE | I77: 420 COLLEGE | J77: K8N5T1 | K77: ACTIVE | L77: E562 | M77: 3313254 | N77: EMMERSON PACKAGING | O77: 3313254E562 | P77: EMMERSON PACKAGING | Q77: EMMERSON PACKAGING HOLDINGS INC.
A78: =IF(OR(Q78<>"",R78<>""),"Y","N") -> Y | B78: WILFREDA EDWARD-DOLCY | C78: 15360 | D78: EMO HOSPITAL | E78: N | F78: EMO HOSPITAL | G78: ON | H78: EMO | I78: 260 FRONT | J78: P0W 1E0 | K78: ACTIVE | L78: E521 | M78: 15360 | N78: EMO HOSPITAL | O78: 15360E521 | P78: EMO HOSPITAL | Q78: EMO HOSPITAL
A79: =IF(OR(Q79<>"",R79<>""),"Y","N") -> Y | B79: WILFREDA EDWARD-DOLCY | C79: 2533341 | D79: EMO TRANS WEST CDA LIMITED | E79: N | F79: EMO TRANS (WEST CDA) LIMITED | G79: BC | H79: RICHMOND | I79: 13700 MAYFIELD 1115 | J79: V6V2E4 | K79: ACTIVE | L79: E536 | M79: 2533341 | N79: EMO TRANS WEST CDA LIMITED | O79: 2533341E536 | P79: EMO TRANS WEST CDA LIMITED | Q79: EMO TRANS (WEST CDA) LIMITED
A80: =IF(OR(Q80<>"",R80<>""),"Y","N") -> Y | B80: WILFREDA EDWARD-DOLCY | C80: 16307 | D80: EMPACK | E80: N | F80: EMPACK | G80: ON | H80: MISSISSAUGA | I80: 1062 WESTPORT CRESCENT | J80: L5T 1G1 | K80: ACTIVE | L80: E512 | M80: 16307 | N80: EMPACK | O80: 16307E512 | P80: EMPACK | Q80: EMPACK SPRAYTECH INC.
A81: =IF(OR(Q81<>"",R81<>""),"Y","N") -> Y | B81: WILFREDA EDWARD-DOLCY | C81: 12372 | D81: EMPCO FAB LTD | E81: N | F81: EMPCO FAB LTD. | G81: ON | H81: WHITBY | I81: 910 HOPKINS ST. | J81: L1N 6A9 | K81: ACTIVE | L81: E512 | M81: 12372 | N81: EMPCO FAB LTD | O81: 12372E512 | P81: EMPCO FAB LTD | Q81: EMPCO (CANADA) LTD.
A82: =IF(OR(Q82<>"",R82<>""),"Y","N") -> Y | B82: WILFREDA EDWARD-DOLCY | C82: 1073893 | D82: EMPIRE STEVEDORING CO LTD | E82: Y | F82: EMPIRE STEVEDORING CO. LTD. | G82: QC | H82: MONTREAL | I82: 851 DES MOULINS | J82: H3C6V9 | K82: ACTIVE | L82: E516 | M82: 1073893 | N82: EMPIRE STEVEDORING CO LTD | O82: 1073893E516 | P82: EMPIRE STEVEDORING CO LTD | Q82: EMPIRE STEVEDORING CO. LTD. | R82: COMPAGNIE D'ARRIMAGE EMPIRE LTEE
A83: =IF(OR(Q83<>"",R83<>""),"Y","N") -> Y | B83: WILFREDA EDWARD-DOLCY | C83: 2033264 | D83: EMPRESS PAINTING | E83: N | F83: Empress Painting | G83: BC | H83: VICTORIA | I83: 863 VIEWFIELD | J83: V9A4V2 | K83: ACTIVE | L83: E516 | M83: 2033264 | N83: EMPRESS PAINTING | O83: 2033264E516 | P83: EMPRESS PAINTING | Q83: EMPRESS PAINTING LTD.
A84: =IF(OR(Q84<>"",R84<>""),"Y","N") -> Y | B84: WILFREDA EDWARD-DOLCY | C84: 12374 | D84: EMSEAL CORP | E84: N | F84: EMSEAL CORP. | G84: ON | H84: TORONTO | I84: 120 CARRIER DRIVE | J84: M9W 5R1 | K84: ACTIVE | L84: E524 | M84: 12374 | N84: EMSEAL CORP | O84: 12374E524 | P84: EMSEAL CORP | Q84: EMSEAL Joint Systems Ltd.
A85: =IF(OR(Q85<>"",R85<>""),"Y","N") -> Y | B85: WILFREDA EDWARD-DOLCY | C85: 10008 | D85: ENBRIDGE PIPELINE INC | E85: N | F85: ENBRIDGE PIPELINE INC. | G85: SK | H85: REGINA | I85: 119E 9TH AVENUE NORTH | J85: S4P 3B2 | K85: ACTIVE | L85: E516 | M85: 8781 | N85: ENBRIDGE PIPELINES NW INC | O85: 8781E516 | P85: ENBRIDGE PIPELINES NW INC | Q85: ENBRIDGE PIPELINES INC. | R85: PIPELINES ENBRIDGE INC.
A86: =IF(OR(Q86<>"",R86<>""),"Y","N") -> Y | B86: WILFREDA EDWARD-DOLCY | C86: 17966 | D86: ENBRIDGE PIPELINES INC | E86: Y | F86: ENBRIDGE PIPELINES INC. | G86: MB | H86: CROMER | I86: BOX 52 HWY 256 | J86: R0M 0J0 | K86: ACTIVE | L86: E516 | M86: 8781 | N86: ENBRIDGE PIPELINES NW INC | O86: 8781E516 | P86: ENBRIDGE PIPELINES NW INC | Q86: ENBRIDGE PIPELINES INC. | R86: PIPELINES ENBRIDGE INC.
A87: =IF(OR(Q87<>"",R87<>""),"Y","N") -> Y | B87: WILFREDA EDWARD-DOLCY | C87: 8781 | D87: ENBRIDGE PIPELINES NW INC | E87: N | F87: ENBRIDGE PIPELINES (NW) INC. | G87: NT | H87: NORMAN WELLS | I87: BOX 280 | J87: X0E-0V0 | K87: ACTIVE | L87: E516 | M87: 8781 | N87: ENBRIDGE PIPELINES NW INC | O87: 8781E516 | P87: ENBRIDGE PIPELINES NW INC | Q87: ENBRIDGE PIPELINES INC. | R87: PIPELINES ENBRIDGE INC.
A88: =IF(OR(Q88<>"",R88<>""),"Y","N") -> Y | B88: WILFREDA EDWARD-DOLCY | C88: 10417 | D88: ENBRIDGE PIPELINES NW LTD | E88: N | F88: ENBRIDGE PIPELINES (NW) LTD | G88: NT | H88: FORT SIMPSON | I88: BOX 495 | J88: X0E 0N0 | K88: ACTIVE | L88: E516 | M88: 8781 | N88: ENBRIDGE PIPELINES NW INC | O88: 8781E516 | P88: ENBRIDGE PIPELINES NW INC | Q88: ENBRIDGE PIPELINES INC. | R88: PIPELINES ENBRIDGE INC.
A89: =IF(OR(Q89<>"",R89<>""),"Y","N") -> Y | B89: WILFREDA EDWARD-DOLCY | C89: 9674 | D89: ENBRIDGE PIPELINES SASKATCHEWAN INC | E89: N | F89: ENBRIDGE PIPELINES (SASKATCHEWAN) INC | G89: SK | H89: ESTEVAN | I89: 402 KENSINGTON AVE BOX 1400 | J89: S4A 2K9 | K89: ACTIVE | L89: E516 | M89: 9674 | N89: ENBRIDGE PIPELINES SASKATCHEWAN INC | O89: 8781E516 | P89: ENBRIDGE PIPELINES SASKATCHEWAN INC | Q89: ENBRIDGE PIPELINES INC. | R89: PIPELINES ENBRIDGE INC.
A90: =IF(OR(Q90<>"",R90<>""),"Y","N") -> Y | B90: WILFREDA EDWARD-DOLCY | C90: 23077 | D90: ENCANA CORPORATION | E90: N | F90: ENCANA CORPORATION | G90: BC | H90: DAWSON CREEK | I90: PO BOX 960 - 37 VIC TURNER ROAD N55.73885 BY W120.16620 | J90: V1G4G4 | K90: ACTIVE | L90: E525 | M90: 23077 | N90: ENCANA CORPORATION | O90: 23077E525 | P90: ENCANA CORPORATION | Q90: ENCANA CORPORATION | S90: probably inactive
A91: =IF(OR(Q91<>"",R91<>""),"Y","N") -> Y | B91: WILFREDA EDWARD-DOLCY | C91: 7177 | D91: ENCRE DIMPRIMERIE FRONTIERE LTEE | E91: N | F91: ENCRE D'IMPRIMERIE FRONTIERE LTEE | G91: QC | H91: MONTREAL | I91: 3770 FRANÇOIS-BRICAULT | J91: H1B5X3 | K91: ACTIVE | L91: E526 | M91: 7177 | N91: ENCRE DIMPRIMERIE FRONTIERE LTEE | O91: 7177E526 | P91: ENCRE DIMPRIMERIE FRONTIERE LTEE | Q91: ENCRES D'IMPRIMERIE FRONTIERE LTÉE
A92: =IF(OR(Q92<>"",R92<>""),"Y","N") -> Y | B92: WILFREDA EDWARD-DOLCY | C92: 12393 | D92: ENDICOTT FUELS AND PROPANE LIMITED | E92: Y | F92: ENDICOTT FUELS & PROPANE LIMITED | G92: ON | H92: PETERBOROUGH | I92: 700 ASHBURNHAM DRIVE | J92: K9L 1T7 | K92: ACTIVE | L92: E532 | M92: 12393 | N92: ENDICOTT FUELS AND PROPANE LIMITED | O92: 12393E532 | P92: ENDICOTT FUELS AND PROPANE LIMITED | Q92: ENDICOTT FUELS & PROPANE LIMITED
A93: =IF(OR(Q93<>"",R93<>""),"Y","N") -> Y | B93: WILFREDA EDWARD-DOLCY | C93: 2033131 | D93: ENDOCRINE RESEARCH SOCIETY | E93: N | F93: Endocrine Research Society | G93: BC | H93: VANCOUVER | I93: 1033 DAVIE 410 | J93: V6E1M7 | K93: ACTIVE | L93: E532 | M93: 2033131 | N93: ENDOCRINE RESEARCH SOCIETY | O93: 2033131E532 | P93: ENDOCRINE RESEARCH SOCIETY | Q93: ENDOCRINE RESEARCH SOCIETY | S93: not found in DB
A94: =IF(OR(Q94<>"",R94<>""),"Y","N") -> Y | B94: WILFREDA EDWARD-DOLCY | C94: 7979 | D94: ENDUITS STEF | E94: Y | F94: ENDUITS STEF | G94: QC | H94: SHERBROOKE | I94: 4365 ROBITAILLE | J94: J1L-2K2 | K94: ACTIVE | L94: E533 | M94: 7979 | N94: ENDUITS STEF | O94: 7979E533 | P94: ENDUITS STEF | Q94: ENDUITS STEF INC.
A95: =IF(OR(Q95<>"",R95<>""),"Y","N") -> Y | B95: WILFREDA EDWARD-DOLCY | C95: 4112765 | D95: ENDURA MANUFACTURING CO LTD | E95: N | F95: Endura Manufacturing Co Ltd. | G95: AB | H95: EDMONTON | I95: 12425 149 | J95: T5L2J6 | K95: ACTIVE | L95: E536 | M95: 4112765 | N95: ENDURA MANUFACTURING CO LTD | O95: 4112765E536 | P95: ENDURA MANUFACTURING CO LTD | Q95: ENDURA MANUFACTURING COMPANY LIMITED
A96: =IF(OR(Q96<>"",R96<>""),"Y","N") -> Y | B96: WILFREDA EDWARD-DOLCY | C96: 23179 | D96: ENERGETIC OILFIELD SERVICES | E96: N | F96: ENERGETIC OILFIELD SERVICES | G96: AB | H96: EDSON | I96: EDSON | J96: I7E1L9 | K96: ACTIVE | L96: E562 | M96: 23179 | N96: ENERGETIC OILFIELD SERVICES | O96: 21148E562 | P96: ENERGETIC OILFIELD SERVICES | Q96: ENERGETIC SERVICES INC.
A97: =IF(OR(Q97<>"",R97<>""),"Y","N") -> Y | B97: WILFREDA EDWARD-DOLCY | C97: 21148 | D97: ENERGETIC SERVICES INC | E97: N | F97: ENERGETIC SERVICES INC | G97: BC | H97: FORT ST. JOHN | I97: MILE 54 ALASKA HWY PO BOX 6639 N56.30189 BY W121.00131 | J97: VIJ 4J1 | K97: ACTIVE | L97: E562 | M97: 21148 | N97: ENERGETIC SERVICES INC | O97: 21148E562 | P97: ENERGETIC SERVICES INC | Q97: ENERGETIC SERVICES INC.
A98: =IF(OR(Q98<>"",R98<>""),"Y","N") -> Y | B98: WILFREDA EDWARD-DOLCY | C98: 23246 | D98: ENERGETIC SERVICES INC | E98: N | F98: ENERGETIC SERVICES INC. | G98: BC | H98: FORT NELSON | I98: MILE 293 ALASKA HWY, #1629 BCR IND. PARK 34 BARBER WAY - N58.74714 BY W122.68210 | J98: VOC1RO | K98: ACTIVE | L98: E562 | M98: 21148 | N98: ENERGETIC SERVICES INC | O98: 21148E562 | P98: ENERGETIC SERVICES INC | Q98: ENERGETIC SERVICES INC.
A99: =IF(OR(Q99<>"",R99<>""),"Y","N") -> Y | B99: WILFREDA EDWARD-DOLCY | C99: 23746 | D99: ENERGETIC SERVICES INC | E99: N | F99: ENERGETIC SERVICES INC. | G99: AB | H99: GRANDE PRAIRIE | I99: 13701 -99ST | J99: T8V7N9 | K99: ACTIVE | L99: E562 | M99: 21148 | N99: ENERGETIC SERVICES INC | O99: 21148E562 | P99: ENERGETIC SERVICES INC | Q99: ENERGETIC SERVICES INC.
A100: =IF(OR(Q100<>"",R100<>""),"Y","N") -> Y | B100: WILFREDA EDWARD-DOLCY | C100: 6276 | D100: ENERGIE ATOMIQUE DU CANADA | E100: N | F100: ENERGIE ATOMIQUE DU CANADA | G100: QC | H100: BECANCOUR | I100: 4160 LA PRADE | J100: G9H0B6 | K100: ACTIVE | L100: E562 | M100: 6276 | N100: ENERGIE ATOMIQUE DU CANADA | O100: 6276E562 | P100: ENERGIE ATOMIQUE DU CANADA | Q100: ATOMIC ENERGY OF CANADA LIMITED | R100: L'ENERGIE ATOMIQUE DU CANADA LIMITEE
...

Sheet SUMMARY
A1: Start Date | B1: 44167
A2: End Date
A4: ALL SITES
A5: NAMES | B5: ASSIGNED | C5: COMPLETE | D5: %
A6: QIONG LI | B6: =COUNTIF(MATCHRESULTS!$B$2:$B$13000,SUMMARY!A6) -> 2477 | C6: =COUNTIFS(MATCHRESULTS!$B$2:$B$13000,SUMMARY!A6,MATCHRESULTS!$A$2:$A$13000,"Y") -> 2414 | D6: =C6/B6 -> 0.97456601
A7: DESMOND YELLAND | B7: =COUNTIF(MATCHRESULTS!$B$2:$B$13000,SUMMARY!A7) -> 2477 | C7: =COUNTIFS(MATCHRESULTS!$B$2:$B$13000,SUMMARY!A7,MATCHRESULTS!$A$2:$A$13000,"Y") -> 603 | D7: =C7/B7 -> 0.24343964
A8: WILFREDA EDWARD-DOLCY | B8: =COUNTIF(MATCHRESULTS!$B$2:$B$13000,SUMMARY!A8) -> 2477 | C8: =COUNTIFS(MATCHRESULTS!$B$2:$B$13000,SUMMARY!A8,MATCHRESULTS!$A$2:$A$13000,"Y") -> 1179 | D8: =C8/B8 -> 0.47597901
A9: MITCHELL JACKSON | B9: =COUNTIF(MATCHRESULTS!$B$2:$B$13000,SUMMARY!A9) -> 2477 | C9: =COUNTIFS(MATCHRESULTS!$B$2:$B$13000,SUMMARY!A9,MATCHRESULTS!$A$2:$A$13000,"Y") -> 195 | D9: =C9/B9 -> 0.078724263
A10: TATIANA KOLECHKINA | B10: =COUNTIF(MATCHRESULTS!$B$2:$B$13000,SUMMARY!A10) -> 2477 | C10: =COUNTIFS(MATCHRESULTS!$B$2:$B$13000,SUMMARY!A10,MATCHRESULTS!$A$2:$A$13000,"Y") -> 2477 | D10: =C10/B10 -> 1
A11: TOTAL | B11: =SUM(B6:B10) -> 12385 | C11: =SUM(C6:C10) -> 6868 | D11: =C11/B11 -> 0.55454178
A13: Planned2021="Y"
A14: NAMES | B14: ASSIGNED | C14: COMPLETE | D14: %
A15: QIONG LI | B15: =COUNTIFS(MATCHRESULTS!$B$2:$B$13000,SUMMARY!A15,MATCHRESULTS!$E$2:$E$13000,"Y") -> 511 | C15: =COUNTIFS(MATCHRESULTS!$B$2:$B$13000,SUMMARY!A15,MATCHRESULTS!$A$2:$A$13000,"Y",MATCHRESULTS!$E$2:$E$13000,"Y") -> 503 | D15: =C15/B15 -> 0.98434442
A16: DESMOND YELLAND | B16: =COUNTIFS(MATCHRESULTS!$B$2:$B$13000,SUMMARY!A16,MATCHRESULTS!$E$2:$E$13000,"Y") -> 573 | C16: =COUNTIFS(MATCHRESULTS!$B$2:$B$13000,SUMMARY!A16,MATCHRESULTS!$A$2:$A$13000,"Y",MATCHRESULTS!$E$2:$E$13000,"Y") -> 435 | D16: =C16/B16 -> 0.7591623
A17: WILFREDA EDWARD-DOLCY | B17: =COUNTIFS(MATCHRESULTS!$B$2:$B$13000,SUMMARY!A17,MATCHRESULTS!$E$2:$E$13000,"Y") -> 536 | C17: =COUNTIFS(MATCHRESULTS!$B$2:$B$13000,SUMMARY!A17,MATCHRESULTS!$A$2:$A$13000,"Y",MATCHRESULTS!$E$2:$E$13000,"Y") -> 536 | D17: =C17/B17 -> 1
A18: MITCHELL JACKSON | B18: =COUNTIFS(MATCHRESULTS!$B$2:$B$13000,SUMMARY!A18,MATCHRESULTS!$E$2:$E$13000,"Y") -> 546 | C18: =COUNTIFS(MATCHRESULTS!$B$2:$B$13000,SUMMARY!A18,MATCHRESULTS!$A$2:$A$13000,"Y",MATCHRESULTS!$E$2:$E$13000,"Y") -> 128 | D18: =C18/B18 -> 0.23443223
A19: TATIANA KOLECHKINA | B19: =COUNTIFS(MATCHRESULTS!$B$2:$B$13000,SUMMARY!A19,MATCHRESULTS!$E$2:$E$13000,"Y") -> 810 | C19: =COUNTIFS(MATCHRESULTS!$B$2:$B$13000,SUMMARY!A19,MATCHRESULTS!$A$2:$A$13000,"Y",MATCHRESULTS!$E$2:$E$13000,"Y") -> 810 | D19: =C19/B19 -> 1
A20: TOTAL | B20: =SUM(B15:B19) -> 2976 | C20: =SUM(C15:C19) -> 2412 | D20: =C20/B20 -> 0.81048387

Sheet RULES
A2: For consistency, if you have made a decision which could be leveraged for a similar situation later, please record the steps here
A4: 1) ACME SUPPLIES is owned by BUNZL CANADA INC., should have BUNZL's ID
A5: 2) "<name> Co-operative Association Limited" is owned by "Federated Co-operatives Limited"
